{
  "districtId": "ADANA__YUMURTALIK",
  "districtName": "Yumurtalık",
  "neighborhoods": [
    {
      "id": "ASMALI",
      "name": "Asmalı"
    },
    {
      "id": "AYVALIK",
      "name": "Ayvalık"
    },
    {
      "id": "DEMİRTAŞ",
      "name": "Demirtaş"
    },
    {
      "id": "DEVECİUŞAĞI",
      "name": "Deveciuşağı"
    },
    {
      "id": "GÖLOVASI",
      "name": "Gölovası"
    },
    {
      "id": "HAMZALI",
      "name": "Hamzalı"
    },
    {
      "id": "HAYLAZLI",
      "name": "Haylazlı"
    },
    {
      "id": "KALEMLİ",
      "name": "Kalemli"
    },
    {
      "id": "KESMEBURUN",
      "name": "Kesmeburun"
    },
    {
      "id": "KIRMIZIDAM",
      "name": "Kırmızıdam"
    },
    {
      "id": "KUZUPINARI",
      "name": "Kuzupınarı"
    },
    {
      "id": "NARLIÖREN",
      "name": "Narlıören"
    },
    {
      "id": "SUGÖZÜ",
      "name": "Sugözü"
    },
    {
      "id": "AYAS",
      "name": "Ayas"
    },
    {
      "id": "DEVRİŞİYE",
      "name": "Devrişiye"
    },
    {
      "id": "ÖREN",
      "name": "Ören"
    },
    {
      "id": "KEMALPAŞA",
      "name": "Kemalpaşa"
    },
    {
      "id": "KALDIRIM",
      "name": "Kaldırım"
    },
    {
      "id": "ZEYTİNBELİ",
      "name": "Zeytinbeli"
    },
    {
      "id": "AKDENİZ",
      "name": "Akdeniz"
    },
    {
      "id": "AKYUVA",
      "name": "Akyuva"
    },
    {
      "id": "YEŞİLKÖY",
      "name": "Yeşilköy"
    },
    {
      "id": "YENİKÖY",
      "name": "Yeniköy"
    },
    {
      "id": "YUMURTALIK",
      "name": "Yumurtalık"
    }
  ]
}