{
  "districtId": "ANKARA__MAMAK",
  "districtName": "Mamak",
  "neighborhoods": [
    {
      "id": "KUTLUDÜĞÜN",
      "name": "Kutludüğün"
    },
    {
      "id": "DİRİLİŞ",
      "name": "Diriliş"
    },
    {
      "id": "KARŞIYAKA",
      "name": "Karşıyaka"
    },
    {
      "id": "LALAHAN",
      "name": "Lalahan"
    },
    {
      "id": "BAYINDIR",
      "name": "Bayındır"
    },
    {
      "id": "ZİRVEKENT",
      "name": "Zirvekent"
    },
    {
      "id": "ALTINEVLER",
      "name": "Altınevler"
    },
    {
      "id": "GÖKÇEYURT",
      "name": "Gökçeyurt"
    },
    {
      "id": "KIBRISKÖY",
      "name": "Kıbrısköy"
    },
    {
      "id": "KIZILCA",
      "name": "Kızılca"
    },
    {
      "id": "KUSUNLAR",
      "name": "Kusunlar"
    },
    {
      "id": "ORTAKÖY",
      "name": "Ortaköy"
    },
    {
      "id": "ABİDİNPAŞA",
      "name": "Abidinpaşa"
    },
    {
      "id": "AKDERE",
      "name": "Akdere"
    },
    {
      "id": "ALTIAĞAÇ",
      "name": "Altıağaç"
    },
    {
      "id": "ARAPLAR",
      "name": "Araplar"
    },
    {
      "id": "AŞIK_VEYSEL",
      "name": "Aşık Veysel"
    },
    {
      "id": "BAŞAK",
      "name": "Başak"
    },
    {
      "id": "KAYAŞ",
      "name": "Kayaş"
    },
    {
      "id": "BALKİRAZ",
      "name": "Balkiraz"
    },
    {
      "id": "BOĞAZİÇİ",
      "name": "Boğaziçi"
    },
    {
      "id": "BOSTANCIK",
      "name": "Bostancık"
    },
    {
      "id": "CENGİZHAN",
      "name": "Cengizhan"
    },
    {
      "id": "ÇAĞLAYAN",
      "name": "Çağlayan"
    },
    {
      "id": "ÇİĞİLTEPE",
      "name": "Çiğiltepe"
    },
    {
      "id": "DEMİRLİBAHÇE",
      "name": "Demirlibahçe"
    },
    {
      "id": "DERBENT",
      "name": "Derbent"
    },
    {
      "id": "DOSTLAR",
      "name": "Dostlar"
    },
    {
      "id": "DURALİ_ALIÇ",
      "name": "Durali Alıç"
    },
    {
      "id": "DUTLUK",
      "name": "Dutluk"
    },
    {
      "id": "EGE",
      "name": "Ege"
    },
    {
      "id": "EKİN",
      "name": "Ekin"
    },
    {
      "id": "FAHRİ_KORUTÜRK",
      "name": "Fahri Korutürk"
    },
    {
      "id": "GENERAL_ZEKİ_DOĞAN",
      "name": "General Zeki Doğan"
    },
    {
      "id": "GÜLVEREN",
      "name": "Gülveren"
    },
    {
      "id": "HARMAN",
      "name": "Harman"
    },
    {
      "id": "HÜREL",
      "name": "Hürel"
    },
    {
      "id": "HÜSEYİNGAZİ",
      "name": "Hüseyingazi"
    },
    {
      "id": "KARAAĞAÇ",
      "name": "Karaağaç"
    },
    {
      "id": "KARTALTEPE",
      "name": "Kartaltepe"
    },
    {
      "id": "KAZIM_ORBAY",
      "name": "Kazım Orbay"
    },
    {
      "id": "KÖSTENCE",
      "name": "Köstence"
    },
    {
      "id": "KÜÇÜK_KAYAŞ",
      "name": "Küçük Kayaş"
    },
    {
      "id": "MEHTAP",
      "name": "Mehtap"
    },
    {
      "id": "MİSKET",
      "name": "Misket"
    },
    {
      "id": "MUTLU",
      "name": "Mutlu"
    },
    {
      "id": "PEYAMİ_SAFA",
      "name": "Peyami Safa"
    },
    {
      "id": "SAİMEKADIN",
      "name": "Saimekadın"
    },
    {
      "id": "ŞAFAKTEPE",
      "name": "Şafaktepe"
    },
    {
      "id": "ŞAHAP_GÜRLER",
      "name": "Şahap Gürler"
    },
    {
      "id": "ŞAHİNTEPE",
      "name": "Şahintepe"
    },
    {
      "id": "ŞEHİT_CENGİZ_TOPEL",
      "name": "Şehit Cengiz Topel"
    },
    {
      "id": "ŞİRİNTEPE",
      "name": "Şirintepe"
    },
    {
      "id": "TEPECİK",
      "name": "Tepecik"
    },
    {
      "id": "TUZLUÇAYIR",
      "name": "Tuzluçayır"
    },
    {
      "id": "TÜRKÖZÜ",
      "name": "Türközü"
    },
    {
      "id": "ÜREĞİL",
      "name": "Üreğil"
    },
    {
      "id": "YENİ_BAYINDIR",
      "name": "Yeni Bayındır"
    },
    {
      "id": "YEŞİLBAYIR",
      "name": "Yeşilbayır"
    },
    {
      "id": "YUKARI_İMROHOR",
      "name": "Yukarı İmrohor"
    },
    {
      "id": "AKŞEMSETTİN",
      "name": "Akşemsettin"
    },
    {
      "id": "KUTLU",
      "name": "Kutlu"
    },
    {
      "id": "BAHÇELERÜSTÜ",
      "name": "Bahçelerüstü"
    },
    {
      "id": "BAHÇELERİÇİ",
      "name": "Bahçeleriçi"
    }
  ]
}