{
  "districtId": "ANTALYA__KEMER",
  "districtName": "Kemer",
  "neighborhoods": [
    {
      "id": "YENİMAHALLE",
      "name": "Yenimahalle"
    },
    {
      "id": "MERKEZ",
      "name": "Merkez"
    },
    {
      "id": "KİRİŞ",
      "name": "Kiriş"
    },
    {
      "id": "ARSLANBUCAK",
      "name": "Arslanbucak"
    },
    {
      "id": "BELDİBİ",
      "name": "Beldibi"
    },
    {
      "id": "KUZDERE",
      "name": "Kuzdere"
    },
    {
      "id": "BEYCİK",
      "name": "Beycik"
    },
    {
      "id": "OVACIK",
      "name": "Ovacık"
    },
    {
      "id": "ULUPINAR",
      "name": "Ulupınar"
    },
    {
      "id": "TEKİROVA",
      "name": "Tekirova"
    },
    {
      "id": "ÇAMYUVA",
      "name": "Çamyuva"
    },
    {
      "id": "GÖYNÜK",
      "name": "Göynük"
    }
  ]
}