{
  "districtId": "AĞRI__ELEŞKİRT",
  "districtName": "Eleşkirt",
  "neighborhoods": [
    {
      "id": "HÜRRİYET",
      "name": "Hürriyet"
    },
    {
      "id": "İSTİKLAL",
      "name": "İstiklal"
    },
    {
      "id": "KARŞIYAKA",
      "name": "Karşıyaka"
    },
    {
      "id": "KAZIMKARABEKİR",
      "name": "Kazımkarabekir"
    },
    {
      "id": "LOZAN",
      "name": "Lozan"
    },
    {
      "id": "MÜFTÜSELİM",
      "name": "Müftüselim"
    },
    {
      "id": "ESENTEPE",
      "name": "Esentepe"
    },
    {
      "id": "FATİH",
      "name": "Fatih"
    },
    {
      "id": "KARŞIYAKA",
      "name": "Karşıyaka"
    },
    {
      "id": "YEŞİL",
      "name": "Yeşil"
    },
    {
      "id": "AYDINTEPE",
      "name": "Aydıntepe"
    },
    {
      "id": "AŞAĞICİHANBEY",
      "name": "Aşağıcihanbey"
    },
    {
      "id": "DEĞİRMENGEÇİDİ",
      "name": "Değirmengeçidi"
    },
    {
      "id": "GÖKÇAYIR",
      "name": "Gökçayır"
    },
    {
      "id": "KARŞIYAKA",
      "name": "Karşıyaka"
    },
    {
      "id": "CUMHURİYET",
      "name": "Cumhuriyet"
    },
    {
      "id": "OKLAVALI",
      "name": "Oklavalı"
    },
    {
      "id": "ŞEHİT_ENGİN",
      "name": "Şehit Engin"
    },
    {
      "id": "ESENTEPE",
      "name": "Esentepe"
    },
    {
      "id": "YEŞİLYURT",
      "name": "Yeşilyurt"
    }
  ]
}