{
  "districtId": "BALIKESIR__AYVALIK",
  "districtName": "Ayvalık",
  "neighborhoods": [
    {
      "id": "150_EVLER",
      "name": "150 Evler"
    },
    {
      "id": "AKCAPINAR",
      "name": "Akçapınar"
    },
    {
      "id": "ALI_CETINKAYA",
      "name": "Ali Çetinkaya"
    },
    {
      "id": "ALTINOVA",
      "name": "Altınova"
    },
    {
      "id": "BAGYUZU",
      "name": "Bağyüzü"
    },
    {
      "id": "BESIKTEPE",
      "name": "Beşiktepe"
    },
    {
      "id": "BULUTCESME",
      "name": "Bulutçeşme"
    },
    {
      "id": "CAKMAK",
      "name": "Çakmak"
    },
    {
      "id": "CAMOBA",
      "name": "Çamoba"
    },
    {
      "id": "FETHIYE",
      "name": "Fethiye"
    },
    {
      "id": "FEVZIPASAVEHBIBEY",
      "name": "Fevzipaşa-vehbibey"
    },
    {
      "id": "GAZI_KEMAL_PASA",
      "name": "Gazi Kemal Paşa"
    },
    {
      "id": "HACIVELILER",
      "name": "Hacıveliler"
    },
    {
      "id": "HAMDIBEY",
      "name": "Hamdibey"
    },
    {
      "id": "HAYRETTINPASA",
      "name": "Hayrettinpaşa"
    },
    {
      "id": "ISMETPASA",
      "name": "İsmetpaşa"
    },
    {
      "id": "KARAAYIT",
      "name": "Karaayıt"
    },
    {
      "id": "KAZIM_KARABEKIR",
      "name": "Kazım Karabekir"
    },
    {
      "id": "KIRCALAR",
      "name": "Kırcalar"
    },
    {
      "id": "KUCUKKOY",
      "name": "Küçükköy"
    },
    {
      "id": "MITHATPASA",
      "name": "Mithatpaşa"
    },
    {
      "id": "MURATELI",
      "name": "Murateli"
    },
    {
      "id": "MUTLU",
      "name": "Mutlu"
    },
    {
      "id": "NAMIK_KEMAL",
      "name": "Namık Kemal"
    },
    {
      "id": "ODABURNU",
      "name": "Odaburnu"
    },
    {
      "id": "SAHIL_KENT",
      "name": "Sahil Kent"
    },
    {
      "id": "SAKARYA",
      "name": "Sakarya"
    },
    {
      "id": "SEFA_CAMLIK",
      "name": "Sefa Çamlık"
    },
    {
      "id": "TIFILLAR",
      "name": "Tıfıllar"
    },
    {
      "id": "TURKOZU",
      "name": "Türközü"
    },
    {
      "id": "UCKABAAGAC",
      "name": "Üçkabaağaç"
    },
    {
      "id": "YENI",
      "name": "Yeni"
    },
    {
      "id": "YENIKOY",
      "name": "Yeniköy"
    },
    {
      "id": "ZEKIBEY",
      "name": "Zekibey"
    }
  ]
}