{
  "districtId": "BURSA__HARMANCIK",
  "districtName": "Harmancık",
  "neighborhoods": [
    {
      "id": "ECE",
      "name": "Ece"
    },
    {
      "id": "MERKEZ",
      "name": "Merkez"
    },
    {
      "id": "ÇAMOĞLU",
      "name": "Çamoğlu"
    },
    {
      "id": "SAÇAKLI",
      "name": "Saçaklı"
    },
    {
      "id": "AKPINAR",
      "name": "Akpınar"
    },
    {
      "id": "ALUTÇA",
      "name": "Alutça"
    },
    {
      "id": "BALATDANİŞMENT",
      "name": "Balatdanişment"
    },
    {
      "id": "BALLISARAY",
      "name": "Ballısaray"
    },
    {
      "id": "BEKDEMİRLER",
      "name": "Bekdemirler"
    },
    {
      "id": "ÇAKMAK",
      "name": "Çakmak"
    },
    {
      "id": "ÇATALSÖĞÜT",
      "name": "Çatalsöğüt"
    },
    {
      "id": "DEDEBALI",
      "name": "Dedebalı"
    },
    {
      "id": "DELİCEGÜNEY",
      "name": "Delicegüney"
    },
    {
      "id": "DUTLUCA",
      "name": "Dutluca"
    },
    {
      "id": "GEDİKÖREN",
      "name": "Gedikören"
    },
    {
      "id": "GÖKÇELER",
      "name": "Gökçeler"
    },
    {
      "id": "GÜLÖZÜ",
      "name": "Gülözü"
    },
    {
      "id": "HARMANCIKAKALAN",
      "name": "Harmancıkakalan"
    },
    {
      "id": "HOBANDANİŞMENT",
      "name": "Hobandanişment"
    },
    {
      "id": "ILICAKSU",
      "name": "Ilıcaksu"
    },
    {
      "id": "İSHAKLAR",
      "name": "İshaklar"
    },
    {
      "id": "KARACA",
      "name": "Karaca"
    },
    {
      "id": "KEPEKDERE",
      "name": "Kepekdere"
    },
    {
      "id": "KIÇMANLAR",
      "name": "Kıçmanlar"
    },
    {
      "id": "KILAVUZLAR",
      "name": "Kılavuzlar"
    },
    {
      "id": "KOCAPINAR",
      "name": "Kocapınar"
    },
    {
      "id": "KOZLUCA",
      "name": "Kozluca"
    },
    {
      "id": "NALBANT",
      "name": "Nalbant"
    },
    {
      "id": "OKÇULAR",
      "name": "Okçular"
    },
    {
      "id": "YAYABAŞI",
      "name": "Yayabaşı"
    },
    {
      "id": "YEŞİLYURT",
      "name": "Yeşilyurt"
    }
  ]
}