{
  "districtId": "DENIZLI__CARDAK",
  "districtName": "Çardak",
  "neighborhoods": [
    {
      "id": "AYVAZ",
      "name": "Ayvaz"
    },
    {
      "id": "BAHCELIEVLER",
      "name": "Bahçelievler"
    },
    {
      "id": "BEYLERLI",
      "name": "Beylerli"
    },
    {
      "id": "CUMHURIYET",
      "name": "Cumhuriyet"
    },
    {
      "id": "CALTI",
      "name": "Çaltı"
    },
    {
      "id": "CINAR",
      "name": "Çınar"
    },
    {
      "id": "GEMISLI",
      "name": "Gemişli"
    },
    {
      "id": "GEMISPINARI",
      "name": "Gemişpınarı"
    },
    {
      "id": "GOLCUK",
      "name": "Gölcük"
    },
    {
      "id": "HAYRIYE",
      "name": "Hayriye"
    },
    {
      "id": "HURRIYET",
      "name": "Hürriyet"
    },
    {
      "id": "ISTIKLAL",
      "name": "İstiklal"
    },
    {
      "id": "SARAY",
      "name": "Saray"
    },
    {
      "id": "SOGUTLU",
      "name": "Söğütlü"
    },
    {
      "id": "SOGUTOZU",
      "name": "Söğütözü"
    }
  ]
}