{
  "districtId": "ERZURUM__CAT",
  "districtName": "Çat",
  "neighborhoods": [
    {
      "id": "AGAKOY",
      "name": "Ağaköy"
    },
    {
      "id": "ASAGICAT",
      "name": "Aşağıçat"
    },
    {
      "id": "BABADERESI",
      "name": "Babaderesi"
    },
    {
      "id": "BAGLICA",
      "name": "Bağlıca"
    },
    {
      "id": "BARDAKCI",
      "name": "Bardakçı"
    },
    {
      "id": "BASKOY",
      "name": "Başköy"
    },
    {
      "id": "BAYINDIR",
      "name": "Bayındır"
    },
    {
      "id": "BOZYAZI",
      "name": "Bozyazı"
    },
    {
      "id": "BUDAKLAR",
      "name": "Budaklar"
    },
    {
      "id": "CAYIRTEPE",
      "name": "Çayırtepe"
    },
    {
      "id": "CIMENOZU",
      "name": "Çimenözü"
    },
    {
      "id": "CIRISLI",
      "name": "Çirişli"
    },
    {
      "id": "CUKURCAYIR",
      "name": "Çukurçayır"
    },
    {
      "id": "DEGIRMENLI",
      "name": "Değirmenli"
    },
    {
      "id": "ELMAPINAR",
      "name": "Elmapınar"
    },
    {
      "id": "GOBEKOREN",
      "name": "Göbekören"
    },
    {
      "id": "GOKCESEYH",
      "name": "Gökçeşeyh"
    },
    {
      "id": "GOLKOY",
      "name": "Gölköy"
    },
    {
      "id": "HATUNKOY",
      "name": "Hatunköy"
    },
    {
      "id": "ISKINLI",
      "name": "İşkinli"
    },
    {
      "id": "KAPLICA",
      "name": "Kaplıca"
    },
    {
      "id": "KARABEY",
      "name": "Karabey"
    },
    {
      "id": "KARACA",
      "name": "Karaca"
    },
    {
      "id": "KARASEYH",
      "name": "Karaşeyh"
    },
    {
      "id": "KIZILCA",
      "name": "Kızılca"
    },
    {
      "id": "KOSELER",
      "name": "Köseler"
    },
    {
      "id": "KUMASLI",
      "name": "Kumaşlı"
    },
    {
      "id": "KURBANLI",
      "name": "Kurbanlı"
    },
    {
      "id": "MOLLAOMER",
      "name": "Mollaömer"
    },
    {
      "id": "MURATCAYIRI",
      "name": "Muratçayırı"
    },
    {
      "id": "OYUKLU",
      "name": "Oyuklu"
    },
    {
      "id": "PARMAKSIZ",
      "name": "Parmaksız"
    },
    {
      "id": "SALTAS",
      "name": "Saltaş"
    },
    {
      "id": "SARIKASIK",
      "name": "Sarıkaşık"
    },
    {
      "id": "SARIKAYA",
      "name": "Sarıkaya"
    },
    {
      "id": "SOGUKPINAR",
      "name": "Soğukpınar"
    },
    {
      "id": "SOBECAYIR",
      "name": "Söbeçayır"
    },
    {
      "id": "SEYHHASAN",
      "name": "Şeyhhasan"
    },
    {
      "id": "TASAGIL",
      "name": "Taşağıl"
    },
    {
      "id": "TUZLATASI",
      "name": "Tuzlataşı"
    },
    {
      "id": "TUZLUCA",
      "name": "Tuzluca"
    },
    {
      "id": "YARMAK",
      "name": "Yarmak"
    },
    {
      "id": "YAVI",
      "name": "Yavi"
    },
    {
      "id": "YAYLASUYU",
      "name": "Yaylasuyu"
    },
    {
      "id": "YUKARICAT",
      "name": "Yukarıçat"
    },
    {
      "id": "AKALAN",
      "name": "Akalan"
    },
    {
      "id": "ATATURK",
      "name": "Atatürk"
    },
    {
      "id": "AYDINLAR",
      "name": "Aydınlar"
    },
    {
      "id": "BAHSAYIS",
      "name": "Bahşayiş"
    },
    {
      "id": "BASAK",
      "name": "Başak"
    },
    {
      "id": "BELGRAT",
      "name": "Belgrat"
    },
    {
      "id": "CELEPKOY",
      "name": "Celepköy"
    },
    {
      "id": "CAKIL",
      "name": "Çakıl"
    },
    {
      "id": "CANAKCA",
      "name": "Çanakça"
    },
    {
      "id": "CIFTLIKKOY",
      "name": "Çiftlikköy"
    },
    {
      "id": "DAGYENICE",
      "name": "Dağyenice"
    },
    {
      "id": "ELBASAN",
      "name": "Elbasan"
    },
    {
      "id": "FATIH",
      "name": "Fatih"
    },
    {
      "id": "FERHATPASA",
      "name": "Ferhatpaşa"
    },
    {
      "id": "GOKCEALI",
      "name": "Gökçeali"
    },
    {
      "id": "GUMUSPINAR",
      "name": "Gümüşpınar"
    },
    {
      "id": "HALLACLI",
      "name": "Hallaçlı"
    },
    {
      "id": "HISARBEYLI",
      "name": "Hisarbeyli"
    },
    {
      "id": "IHSANIYE",
      "name": "İhsaniye"
    },
    {
      "id": "INCEGIZ",
      "name": "İnceğiz"
    },
    {
      "id": "IZZETTIN",
      "name": "İzzettin"
    },
    {
      "id": "KABAKCA",
      "name": "Kabakça"
    },
    {
      "id": "KALEICI",
      "name": "Kaleiçi"
    },
    {
      "id": "KALFA",
      "name": "Kalfa"
    },
    {
      "id": "KARACAKOY_MERKEZ",
      "name": "Karacaköy Merkez"
    },
    {
      "id": "KARAMANDERE",
      "name": "Karamandere"
    },
    {
      "id": "KESTANELIK",
      "name": "Kestanelik"
    },
    {
      "id": "KIZILCAALI",
      "name": "Kızılcaali"
    },
    {
      "id": "MURATBEY_MERKEZ",
      "name": "Muratbey Merkez"
    },
    {
      "id": "NAKKAS",
      "name": "Nakkaş"
    },
    {
      "id": "OKLALI",
      "name": "Oklalı"
    },
    {
      "id": "ORMANLI",
      "name": "Ormanlı"
    },
    {
      "id": "OVAYENICE",
      "name": "Ovayenice"
    },
    {
      "id": "ORCUNLU",
      "name": "Örcünlü"
    },
    {
      "id": "ORENCIK",
      "name": "Örencik"
    },
    {
      "id": "SUBASI",
      "name": "Subaşı"
    },
    {
      "id": "YALIKOY",
      "name": "Yalıköy"
    },
    {
      "id": "YAYLACIK",
      "name": "Yaylacık"
    },
    {
      "id": "YAZLIK",
      "name": "Yazlık"
    },
    {
      "id": "CELEBILER",
      "name": "Çelebiler"
    },
    {
      "id": "MERKEZ",
      "name": "Merkez"
    },
    {
      "id": "AKKAYA",
      "name": "Akkaya"
    },
    {
      "id": "DERE",
      "name": "Dere"
    },
    {
      "id": "ELMAKOY",
      "name": "Elmaköy"
    },
    {
      "id": "GOLLER",
      "name": "Göller"
    },
    {
      "id": "GUNDOGDU",
      "name": "Gündoğdu"
    },
    {
      "id": "GUNEY",
      "name": "Güney"
    },
    {
      "id": "GUNEYCE",
      "name": "Güneyce"
    },
    {
      "id": "HASAL",
      "name": "Haşal"
    },
    {
      "id": "HATIPLER",
      "name": "Hatipler"
    },
    {
      "id": "INCIRLI",
      "name": "İncirli"
    },
    {
      "id": "KARAHAMZA",
      "name": "Karahamza"
    },
    {
      "id": "KARAHASAN",
      "name": "Karahasan"
    },
    {
      "id": "KARSIYAKA",
      "name": "Karşıyaka"
    },
    {
      "id": "KAYATEPE",
      "name": "Kayatepe"
    },
    {
      "id": "KECILI",
      "name": "Keçili"
    },
    {
      "id": "KIRAN",
      "name": "Kıran"
    },
    {
      "id": "MADENKOY",
      "name": "Madenköy"
    },
    {
      "id": "MERKEZ",
      "name": "Merkez"
    },
    {
      "id": "ORTAKOY",
      "name": "Ortaköy"
    },
    {
      "id": "SAYACATURK",
      "name": "Sayacatürk"
    },
    {
      "id": "SIRINKOY",
      "name": "Şirinköy"
    },
    {
      "id": "TERIMLI",
      "name": "Terimli"
    },
    {
      "id": "YENI",
      "name": "Yeni"
    },
    {
      "id": "ADNAN_MENDERES",
      "name": "Adnan Menderes"
    },
    {
      "id": "AGACLIK",
      "name": "Ağaçlık"
    },
    {
      "id": "AKCABUK",
      "name": "Akçabük"
    },
    {
      "id": "ALACAYAR",
      "name": "Alacayar"
    },
    {
      "id": "ASAGINARLICA",
      "name": "Aşağınarlıca"
    },
    {
      "id": "ATLIHAN",
      "name": "Atlıhan"
    },
    {
      "id": "BAHCELIEVLER",
      "name": "Bahçelievler"
    },
    {
      "id": "BILGI",
      "name": "Bilgi"
    },
    {
      "id": "BOYUNPINAR",
      "name": "Boyunpınar"
    },
    {
      "id": "CUMHURIYET",
      "name": "Cumhuriyet"
    },
    {
      "id": "CILGA",
      "name": "Çılga"
    },
    {
      "id": "DALBASTI",
      "name": "Dalbastı"
    },
    {
      "id": "DEREBASI",
      "name": "Derebaşı"
    },
    {
      "id": "DOKUZDAM",
      "name": "Dokuzdam"
    },
    {
      "id": "ELIACIK",
      "name": "Eliaçık"
    },
    {
      "id": "GORENTAS",
      "name": "Görentaş"
    },
    {
      "id": "HACIOSMAN",
      "name": "Hacıosman"
    },
    {
      "id": "ISINLI",
      "name": "Işınlı"
    },
    {
      "id": "KACIT",
      "name": "Kaçıt"
    },
    {
      "id": "KARSIYAKA",
      "name": "Karşıyaka"
    },
    {
      "id": "KONALGA",
      "name": "Konalga"
    },
    {
      "id": "KORULU",
      "name": "Korulu"
    },
    {
      "id": "NARLI",
      "name": "Narlı"
    },
    {
      "id": "ONAGIL",
      "name": "Onağıl"
    },
    {
      "id": "OVECEK",
      "name": "Övecek"
    },
    {
      "id": "SELCUKLU",
      "name": "Selçuklu"
    },
    {
      "id": "SIRMALI",
      "name": "Sırmalı"
    },
    {
      "id": "SOZVEREN",
      "name": "Sözveren"
    },
    {
      "id": "SUGELDI",
      "name": "Sugeldi"
    },
    {
      "id": "TEKNECIK",
      "name": "Teknecik"
    },
    {
      "id": "TOYGA",
      "name": "Toyga"
    },
    {
      "id": "UZUNTEKNE",
      "name": "Uzuntekne"
    },
    {
      "id": "YUKARINARLICA",
      "name": "Yukarınarlıca"
    }
  ]
}