{
  "districtId": "HAKKARI__DERECIK",
  "districtName": "Derecik",
  "neighborhoods": [
    {
      "id": "BALKAYA",
      "name": "Balkaya"
    },
    {
      "id": "GUNEY",
      "name": "Güney"
    },
    {
      "id": "GURMESE",
      "name": "Gürmeşe"
    },
    {
      "id": "HACIBEY",
      "name": "Hacıbey"
    },
    {
      "id": "MERKEZ",
      "name": "Merkez"
    },
    {
      "id": "ORTA",
      "name": "Orta"
    },
    {
      "id": "RIZE",
      "name": "Rize"
    },
    {
      "id": "UCYAN",
      "name": "Üçyan"
    },
    {
      "id": "VAPURTEPE",
      "name": "Vapurtepe"
    }
  ]
}