{
  "districtId": "ISPARTA__KECIBORLU",
  "districtName": "Keçiborlu",
  "neighborhoods": [
    {
      "id": "ASAGI",
      "name": "Aşağı"
    },
    {
      "id": "CUMHURIYET",
      "name": "Cumhuriyet"
    },
    {
      "id": "HACI_KOYU",
      "name": "Hacı Köyü"
    },
    {
      "id": "HASANBEY",
      "name": "Hasanbey"
    },
    {
      "id": "KAYA",
      "name": "Kaya"
    },
    {
      "id": "KUKURT",
      "name": "Kükürt"
    },
    {
      "id": "ORTA",
      "name": "Orta"
    },
    {
      "id": "TOKI",
      "name": "Toki"
    },
    {
      "id": "TUZLA",
      "name": "Tuzla"
    },
    {
      "id": "YENICE",
      "name": "Yenice"
    },
    {
      "id": "YUKARI",
      "name": "Yukarı"
    },
    {
      "id": "CUMHURIYET",
      "name": "Cumhuriyet"
    },
    {
      "id": "KUSCULAR",
      "name": "Kuşçular"
    },
    {
      "id": "ORTA",
      "name": "Orta"
    },
    {
      "id": "TEPECIK",
      "name": "Tepecik"
    },
    {
      "id": "YENI",
      "name": "Yeni"
    }
  ]
}