{
  "districtId": "ISTANBUL__ATASEHIR",
  "districtName": "Ataşehir",
  "neighborhoods": [
    {
      "id": "ASIKVEYSEL",
      "name": "Aşıkveysel"
    },
    {
      "id": "ATATURK",
      "name": "Atatürk"
    },
    {
      "id": "BARBAROS",
      "name": "Barbaros"
    },
    {
      "id": "ESATPASA",
      "name": "Esatpaşa"
    },
    {
      "id": "FERHATPASA",
      "name": "Ferhatpaşa"
    },
    {
      "id": "FETIH",
      "name": "Fetih"
    },
    {
      "id": "ICERENKOY",
      "name": "İçerenköy"
    },
    {
      "id": "INONU",
      "name": "İnönü"
    },
    {
      "id": "KAYISDAGI",
      "name": "Kayışdağı"
    },
    {
      "id": "KUCUKBAKKALKOY",
      "name": "Küçükbakkalköy"
    },
    {
      "id": "MEVLANA",
      "name": "Mevlana"
    },
    {
      "id": "MIMAR_SINAN",
      "name": "Mimar Sinan"
    },
    {
      "id": "MUSTAFA_KEMAL",
      "name": "Mustafa Kemal"
    },
    {
      "id": "ORNEK",
      "name": "Örnek"
    },
    {
      "id": "YENI_CAMLICA",
      "name": "Yeni Çamlıca"
    },
    {
      "id": "YENISAHRA",
      "name": "Yenisahra"
    },
    {
      "id": "YENISEHIR",
      "name": "Yenişehir"
    }
  ]
}