{
  "districtId": "İZMİR__BORNOVA",
  "districtName": "Bornova",
  "neighborhoods": [
    {
      "id": "ATATÜRK",
      "name": "Atatürk"
    },
    {
      "id": "BARBAROS",
      "name": "Barbaros"
    },
    {
      "id": "BİRLİK",
      "name": "Birlik"
    },
    {
      "id": "ÇAMKULE",
      "name": "Çamkule"
    },
    {
      "id": "ÇINAR",
      "name": "Çınar"
    },
    {
      "id": "DOĞANLAR",
      "name": "Doğanlar"
    },
    {
      "id": "EGEMENLİK",
      "name": "Egemenlik"
    },
    {
      "id": "ERGENE",
      "name": "Ergene"
    },
    {
      "id": "EVKA_3",
      "name": "Evka 3"
    },
    {
      "id": "ERZENE",
      "name": "Erzene"
    },
    {
      "id": "GAZİOSMANPAŞA",
      "name": "Gaziosmanpaşa"
    },
    {
      "id": "GÜRPINAR",
      "name": "Gürpınar"
    },
    {
      "id": "IŞIKLAR",
      "name": "Işıklar"
    },
    {
      "id": "İNÖNÜ",
      "name": "İnönü"
    },
    {
      "id": "KARACAOĞLAN",
      "name": "Karacaoğlan"
    },
    {
      "id": "KAZIM_DİRİK",
      "name": "Kazım Dirik"
    },
    {
      "id": "KEMALPAŞA",
      "name": "Kemalpaşa"
    },
    {
      "id": "KIZILAY",
      "name": "Kızılay"
    },
    {
      "id": "KOŞUKAVAK",
      "name": "Koşukavak"
    },
    {
      "id": "MEVLANA",
      "name": "Mevlana"
    },
    {
      "id": "NALDÖKEN",
      "name": "Naldöken"
    },
    {
      "id": "RAFETPAŞA",
      "name": "Rafetpaşa"
    },
    {
      "id": "TUNA",
      "name": "Tuna"
    },
    {
      "id": "ÜMİT",
      "name": "Ümit"
    },
    {
      "id": "SERİNTEPE",
      "name": "Serintepe"
    },
    {
      "id": "YEŞİLOVA",
      "name": "Yeşilova"
    },
    {
      "id": "YEŞİLÇAM",
      "name": "Yeşilçam"
    },
    {
      "id": "YILDIRIMBEYAZIT",
      "name": "Yıldırımbeyazıt"
    },
    {
      "id": "ZAFER",
      "name": "Zafer"
    },
    {
      "id": "LAKA",
      "name": "Laka"
    },
    {
      "id": "EVKA_4",
      "name": "Evka 4"
    },
    {
      "id": "YUNUSEMRE",
      "name": "Yunusemre"
    },
    {
      "id": "MERİÇ",
      "name": "Meriç"
    },
    {
      "id": "MERKEZ",
      "name": "Merkez"
    },
    {
      "id": "BEŞYOL",
      "name": "Beşyol"
    },
    {
      "id": "ÇAMİÇİ",
      "name": "Çamiçi"
    },
    {
      "id": "ÇİÇEKLİ",
      "name": "Çiçekli"
    },
    {
      "id": "EĞRİDERE",
      "name": "Eğridere"
    },
    {
      "id": "GÖKDERE",
      "name": "Gökdere"
    },
    {
      "id": "KARAÇAM",
      "name": "Karaçam"
    },
    {
      "id": "KAVAKLIDERE",
      "name": "Kavaklıdere"
    },
    {
      "id": "KAYADİBİ",
      "name": "Kayadibi"
    },
    {
      "id": "KURUDERE",
      "name": "Kurudere"
    },
    {
      "id": "SARNIÇ",
      "name": "Sarnıç"
    },
    {
      "id": "YAKAKÖY",
      "name": "Yakaköy"
    }
  ]
}