{
  "districtId": "KARAMAN__ERMENEK",
  "districtName": "Ermenek",
  "neighborhoods": [
    {
      "id": "AKÇAMESCİT",
      "name": "Akçamescit"
    },
    {
      "id": "BAŞPINAR",
      "name": "Başpınar"
    },
    {
      "id": "ÇINARLISU",
      "name": "Çınarlısu"
    },
    {
      "id": "DEĞİRMENLİK",
      "name": "Değirmenlik"
    },
    {
      "id": "GÜLLÜK",
      "name": "Güllük"
    },
    {
      "id": "GÜLPAZAR",
      "name": "Gülpazar"
    },
    {
      "id": "KARALAR",
      "name": "Karalar"
    },
    {
      "id": "KEBENDİBİ",
      "name": "Kebendibi"
    },
    {
      "id": "KEÇİPAZAR",
      "name": "Keçipazar"
    },
    {
      "id": "KEŞİLLİK",
      "name": "Keşillik"
    },
    {
      "id": "MEYDAN",
      "name": "Meydan"
    },
    {
      "id": "ORTA",
      "name": "Orta"
    },
    {
      "id": "SUSAKLI",
      "name": "Susaklı"
    },
    {
      "id": "SANDIKLI",
      "name": "Sandıklı"
    },
    {
      "id": "SEYRAN",
      "name": "Seyran"
    },
    {
      "id": "TAŞBAŞI",
      "name": "Taşbaşı"
    },
    {
      "id": "ARALIK",
      "name": "Aralık"
    },
    {
      "id": "CAMİ",
      "name": "Cami"
    },
    {
      "id": "HABİB",
      "name": "Habib"
    },
    {
      "id": "KIŞLACIK",
      "name": "Kışlacık"
    },
    {
      "id": "ODA",
      "name": "Oda"
    },
    {
      "id": "ORTA",
      "name": "Orta"
    },
    {
      "id": "PINARGÖZÜ",
      "name": "Pınargözü"
    },
    {
      "id": "YENİMAHALLE",
      "name": "Yenimahalle"
    },
    {
      "id": "BUCAK",
      "name": "Bucak"
    },
    {
      "id": "GÖKÇELER",
      "name": "Gökçeler"
    },
    {
      "id": "MERKEZ",
      "name": "Merkez"
    },
    {
      "id": "TEPECİK",
      "name": "Tepecik"
    },
    {
      "id": "TÜRBESEKİ",
      "name": "Türbeseki"
    },
    {
      "id": "ULUKÖY",
      "name": "Uluköy"
    },
    {
      "id": "YUKARI",
      "name": "Yukarı"
    },
    {
      "id": "ÇATALBADEM",
      "name": "Çatalbadem"
    }
  ]
}