{
  "districtId": "KIRSEHIR__KAMAN",
  "districtName": "Kaman",
  "neighborhoods": [
    {
      "id": "BAHCELIEVLER",
      "name": "Bahçelievler"
    },
    {
      "id": "CUMA",
      "name": "Cuma"
    },
    {
      "id": "CIFTLIKLI",
      "name": "Çiftlikli"
    },
    {
      "id": "DARIOZU",
      "name": "Darıözü"
    },
    {
      "id": "GAFFAR",
      "name": "Gaffar"
    },
    {
      "id": "HACIPINAR",
      "name": "Hacıpınar"
    },
    {
      "id": "MUDERRIS",
      "name": "Müderris"
    },
    {
      "id": "ORTA",
      "name": "Orta"
    },
    {
      "id": "SARIUSAGI",
      "name": "Sarıuşağı"
    },
    {
      "id": "YENI",
      "name": "Yeni"
    },
    {
      "id": "ZIYARETTEPE",
      "name": "Ziyarettepe"
    },
    {
      "id": "BAHCELIEVLER",
      "name": "Bahçelievler"
    },
    {
      "id": "CUMHURIYET",
      "name": "Cumhuriyet"
    },
    {
      "id": "ORTA",
      "name": "Orta"
    },
    {
      "id": "YENI",
      "name": "Yeni"
    }
  ]
}