{
  "districtId": "MARDİN__YEŞİLLİ",
  "districtName": "Yeşilli",
  "neighborhoods": [
    {
      "id": "ALIÇLI",
      "name": "Alıçlı"
    },
    {
      "id": "BÜLBÜL",
      "name": "Bülbül"
    },
    {
      "id": "DEREYANI",
      "name": "Dereyanı"
    },
    {
      "id": "KOYUNLU",
      "name": "Koyunlu"
    },
    {
      "id": "KÜTÜKLÜ",
      "name": "Kütüklü"
    },
    {
      "id": "OVAKÖY",
      "name": "Ovaköy"
    },
    {
      "id": "SANCAR",
      "name": "Sancar"
    },
    {
      "id": "UZUNKÖY",
      "name": "Uzunköy"
    },
    {
      "id": "ZEYTİNLİ",
      "name": "Zeytinli"
    },
    {
      "id": "BAHÇEBAŞI",
      "name": "Bahçebaşı"
    },
    {
      "id": "GÜL",
      "name": "Gül"
    },
    {
      "id": "KARŞIYAKA",
      "name": "Karşıyaka"
    },
    {
      "id": "ŞİRİNEVLER",
      "name": "Şirinevler"
    },
    {
      "id": "TEPEBAŞI",
      "name": "Tepebaşı"
    }
  ]
}