{
  "districtId": "USAK__ULUBEY",
  "districtName": "Ulubey",
  "neighborhoods": [
    {
      "id": "AKOLUK",
      "name": "Akoluk"
    },
    {
      "id": "AKPINAR",
      "name": "Akpınar"
    },
    {
      "id": "AYDINLAR",
      "name": "Aydınlar"
    },
    {
      "id": "BASCARDAK",
      "name": "Başçardak"
    },
    {
      "id": "BELENYURT",
      "name": "Belenyurt"
    },
    {
      "id": "CEVIZLIK",
      "name": "Cevizlik"
    },
    {
      "id": "CAGLAYAN",
      "name": "Çağlayan"
    },
    {
      "id": "CATALLI",
      "name": "Çatallı"
    },
    {
      "id": "CUBUKLU",
      "name": "Çubuklu"
    },
    {
      "id": "CUKUR",
      "name": "Çukur"
    },
    {
      "id": "DOGLU",
      "name": "Doğlu"
    },
    {
      "id": "DURAK",
      "name": "Durak"
    },
    {
      "id": "ELMACUKUR",
      "name": "Elmaçukur"
    },
    {
      "id": "EYMUR",
      "name": "Eymür"
    },
    {
      "id": "FINDIKLI",
      "name": "Fındıklı"
    },
    {
      "id": "GUNDUZLU",
      "name": "Gündüzlü"
    },
    {
      "id": "GUVENKOY",
      "name": "Güvenköy"
    },
    {
      "id": "GUVENYURT",
      "name": "Güvenyurt"
    },
    {
      "id": "GUZELYURT",
      "name": "Güzelyurt"
    },
    {
      "id": "HOCAOGLU",
      "name": "Hocaoğlu"
    },
    {
      "id": "KADINCIK",
      "name": "Kadıncık"
    },
    {
      "id": "KALICAK",
      "name": "Kalıcak"
    },
    {
      "id": "KARAKOCA",
      "name": "Karakoca"
    },
    {
      "id": "KARDESLER",
      "name": "Kardeşler"
    },
    {
      "id": "KIRANYAGMUR",
      "name": "Kıranyağmur"
    },
    {
      "id": "KIRAZLIK",
      "name": "Kirazlık"
    },
    {
      "id": "KOSACA",
      "name": "Koşaca"
    },
    {
      "id": "KUMANLAR",
      "name": "Kumanlar"
    },
    {
      "id": "KUMRULU",
      "name": "Kumrulu"
    },
    {
      "id": "OHTAMIS",
      "name": "Ohtamış"
    },
    {
      "id": "OYUMGURGEN",
      "name": "Oyumgürgen"
    },
    {
      "id": "OREN",
      "name": "Ören"
    },
    {
      "id": "REFAHIYE",
      "name": "Refahiye"
    },
    {
      "id": "SAHINKAYA",
      "name": "Şahinkaya"
    },
    {
      "id": "SEKEROLUK",
      "name": "Şekeroluk"
    },
    {
      "id": "SIHLAR",
      "name": "Şıhlar"
    },
    {
      "id": "UZUNMAHMUT",
      "name": "Uzunmahmut"
    },
    {
      "id": "YENIMAHALLE",
      "name": "Yenimahalle"
    },
    {
      "id": "YENISAYACA",
      "name": "Yenisayaca"
    },
    {
      "id": "YOLBASI",
      "name": "Yolbaşı"
    },
    {
      "id": "YUKARIKIZILEN",
      "name": "Yukarıkızılen"
    },
    {
      "id": "ASAGI",
      "name": "Aşağı"
    },
    {
      "id": "AVGAN",
      "name": "Avgan"
    },
    {
      "id": "CAMIKEBIR",
      "name": "Camikebir"
    },
    {
      "id": "DILAVER",
      "name": "Dilaver"
    },
    {
      "id": "EMIRLER",
      "name": "Emirler"
    },
    {
      "id": "GOLBASI",
      "name": "Gölbaşı"
    },
    {
      "id": "UYUKBASI",
      "name": "Üyükbaşı"
    }
  ]
}