{
  "districtId": "VAN__GEVAS",
  "districtName": "Gevaş",
  "neighborhoods": [
    {
      "id": "ABALI",
      "name": "Abalı"
    },
    {
      "id": "ALADUZ",
      "name": "Aladüz"
    },
    {
      "id": "ALTINSAC",
      "name": "Altınsaç"
    },
    {
      "id": "ANAKOY",
      "name": "Anaköy"
    },
    {
      "id": "ATALAN",
      "name": "Atalan"
    },
    {
      "id": "AYDINOCAK",
      "name": "Aydınocak"
    },
    {
      "id": "BAGLAMA",
      "name": "Bağlama"
    },
    {
      "id": "BAHCELIEVLER",
      "name": "Bahçelievler"
    },
    {
      "id": "BARISIK",
      "name": "Barışık"
    },
    {
      "id": "DAGYORE",
      "name": "Dağyöre"
    },
    {
      "id": "DALDERE",
      "name": "Daldere"
    },
    {
      "id": "DEGIRMITAS",
      "name": "Değirmitaş"
    },
    {
      "id": "DEREAGZI",
      "name": "Dereağzı"
    },
    {
      "id": "DILMETAS",
      "name": "Dilmetaş"
    },
    {
      "id": "DOKUZAGAC",
      "name": "Dokuzağaç"
    },
    {
      "id": "ELMALI",
      "name": "Elmalı"
    },
    {
      "id": "GORUNDU",
      "name": "Göründü"
    },
    {
      "id": "GUNDOGAN",
      "name": "Gündoğan"
    },
    {
      "id": "GUZELKONAK",
      "name": "Güzelkonak"
    },
    {
      "id": "HASBEY",
      "name": "Hasbey"
    },
    {
      "id": "HISET",
      "name": "Hişet"
    },
    {
      "id": "IKIZLER",
      "name": "İkizler"
    },
    {
      "id": "INKOY",
      "name": "İnköy"
    },
    {
      "id": "KARSIYAKA",
      "name": "Karşıyaka"
    },
    {
      "id": "KAYALAR",
      "name": "Kayalar"
    },
    {
      "id": "KAZANC",
      "name": "Kazanç"
    },
    {
      "id": "KIZILTAS",
      "name": "Kızıltaş"
    },
    {
      "id": "KOCAK",
      "name": "Koçak"
    },
    {
      "id": "KURULTU",
      "name": "Kurultu"
    },
    {
      "id": "KUSLUK",
      "name": "Kuşluk"
    },
    {
      "id": "ORTA",
      "name": "Orta"
    },
    {
      "id": "PINARBASI",
      "name": "Pınarbaşı"
    },
    {
      "id": "SELIMIYE",
      "name": "Selimiye"
    },
    {
      "id": "TIMAR",
      "name": "Timar"
    },
    {
      "id": "TORELI",
      "name": "Töreli"
    },
    {
      "id": "UGURVEREN",
      "name": "Uğurveren"
    },
    {
      "id": "UYSAL",
      "name": "Uysal"
    },
    {
      "id": "YANIKCAY",
      "name": "Yanıkçay"
    },
    {
      "id": "YEMISLIK",
      "name": "Yemişlik"
    },
    {
      "id": "YOLDONDU",
      "name": "Yoldöndü"
    },
    {
      "id": "YUVA",
      "name": "Yuva"
    }
  ]
}